loly/__init__.py
loly/cli.py
loly/file_collector.py
loly/linter.py
loly/violation.py
loly/policies/__init__.py
loly/policies/base.py
loly/policies/consistent_kv.py
loly/policies/exception_exc_info.py
loly/policies/log_loop.py
loly/presenters/__init__.py
loly/presenters/base.py
loly/presenters/cli.py
llyx-0.1.0.dist-info/METADATA
llyx-0.1.0.dist-info/WHEEL
llyx-0.1.0.dist-info/entry_points.txt
llyx-0.1.0.dist-info/licenses/LICENSE
llyx-0.1.0.dist-info/RECORD
