Metadata-Version: 2.4
Name: llyx
Version: 0.1.0
Summary: llyx - Log Linter for pYthon
License-File: LICENSE
Requires-Python: >=3.9
Requires-Dist: colorama>=0.4.6
Requires-Dist: jsonschema>=4.0.0
Requires-Dist: libcst>=1.0.0
Requires-Dist: pyyaml>=6.0
